storyverse/__init__.py
storyverse/branch_manager.py
storyverse/cli.py
storyverse/commit_store.py
storyverse/content_store.py
storyverse/version_control.py
storyverse-0.1.1.dist-info/LICENSE
storyverse-0.1.1.dist-info/METADATA
storyverse-0.1.1.dist-info/WHEEL
storyverse-0.1.1.dist-info/entry_points.txt
storyverse-0.1.1.dist-info/top_level.txt
storyverse-0.1.1.dist-info/RECORD
